flint/__init__.py
flint/__main__.py
flint/interface.py
flint/maps.py
flint/missions.py
flint/paths.py
flint/routines.py
flint/entities/__init__.py
flint/entities/equipment.py
flint/entities/goods.py
flint/entities/ship.py
flint/entities/solars.py
flint/entities/universe.py
flint/formats/__init__.py
flint/formats/bini.py
flint/formats/dll.py
flint/formats/ini.py
flint/formats/utf.py
fl_flint-0.10.0.dist-info/LICENSE.md
fl_flint-0.10.0.dist-info/METADATA
fl_flint-0.10.0.dist-info/WHEEL
fl_flint-0.10.0.dist-info/top_level.txt
fl_flint-0.10.0.dist-info/RECORD
