Metadata-Version: 2.1
Name: fl-flint
Version: 0.10.0
Summary: A parser for Freelancer and its formats
Home-page: https://github.com/biqqles/flint
Author: biqqles
Author-email: biqqles@protonmail.com
License: UNKNOWN
Platform: UNKNOWN
Classifier: Programming Language :: Python :: 3
Classifier: License :: OSI Approved :: Mozilla Public License 2.0 (MPL 2.0)
Classifier: Operating System :: OS Independent
Classifier: Topic :: Games/Entertainment
Classifier: Intended Audience :: Developers
Classifier: Development Status :: 4 - Beta
Requires-Python: >=3.6
License-File: LICENSE.md
Requires-Dist: dataclassy (>=0.8)
Requires-Dist: deconstruct (>0.2)
